calcbench/__init__.py
calcbench/api_client.py
calcbench/api_query_params.py
calcbench/business_combinations.py
calcbench/companies.py
calcbench/dimensional.py
calcbench/disclosures.py
calcbench/downloaders.py
calcbench/face_statements.py
calcbench/filing.py
calcbench/listener.py
calcbench/metrics.py
calcbench/press_release.py
calcbench/pydantic_to_pandas.py
calcbench/raw_numeric_XBRL.py
calcbench/raw_numeric_non_XBRL.py
calcbench/standardized_numeric.py
calcbench/standardized_parameters.py
calcbench/models/__init__.py
calcbench/models/company.py
calcbench/models/dimensional.py
calcbench/models/disclosure.py
calcbench/models/disclosure_content.py
calcbench/models/disclosure_search_results.py
calcbench/models/face.py
calcbench/models/filing.py
calcbench/models/filing_type.py
calcbench/models/period.py
calcbench/models/period_type.py
calcbench/models/revisions.py
calcbench/models/standardized.py
calcbench/models/trace.py
calcbench_api_client-14.1.3.dist-info/METADATA
calcbench_api_client-14.1.3.dist-info/WHEEL
calcbench_api_client-14.1.3.dist-info/top_level.txt
calcbench_api_client-14.1.3.dist-info/RECORD
